[{"id":"aintmessinround","name":"Ain't Messin 'Round","artist":"Gary Clark Jr.","album_name":"Blak and Blu","anim_tempo":32,"game_origin":"rb4","genre":"rock","master":true,"rank_band":292,"rank_bass":150,"rank_drum":447,"rank_guitar":267,"rank_real_bass":280,"rank_real_guitar":352,"rank_vocals":410,"rating":2,"song_id":5045,"song_length":247179,"sub_genre":"subgenre_rock","vocal_gender":"male","vocal_parts":1,"vocal_tonic_note":4,"year_released":2012},{"id":"albert","name":"Albert","artist":"Eddie Japan","album_name":"Modern Desperation, Pt. II","anim_tempo":64,"game_origin":"rb4","genre":"indierock","master":true,"rank_band":263,"rank_bass":325,"rank_drum":422,"rank_guitar":200,"rank_vocals":163,"rating":1,"song_id":1557880,"song_length":252433,"sub_genre":"subgenre_indierock","vocal_gender":"male","vocal_parts":3,"vocal_tonic_note":7,"year_released":2015},{"id":"alloveryou","name":"All Over You","artist":"Live","album_name":"Throwing Copper","anim_tempo":32,"game_origin":"rb4","genre":"alternative","master":true,"rank_band":264,"rank_bass":258,"rank_drum":297,"rank_guitar":210,"rank_real_bass":220,"rank_real_guitar":199,"rank_vocals":278,"rating":2,"song_id":5057,"song_length":242948,"sub_genre":"subgenre_alternative","vocal_gender":"male","vocal_parts":2,"vocal_tonic_note":1,"year_released":1994},{"id":"apassagetobangkok","name":"A Passage to Bangkok","artist":"Rush","album_name":"2112","anim_tempo":16,"game_origin":"rb4","genre":"prog","master":true,"rank_band":291,"rank_bass":436,"rank_drum":238,"rank_guitar":288,"rank_vocals":402,"rating":2,"song_id":5025,"song_length":215656,"sub_genre":"subgenre_prog","vocal_gender":"male","vocal_parts":1,"vocal_tonic_note":4,"year_released":1976},{"id":"arabella","name":"Arabella","artist":"Arctic Monkeys","album_name":"AM","anim_tempo":16,"game_origin":"rb4","genre":"rock","master":true,"rank_band":215,"rank_bass":388,"rank_drum":151,"rank_guitar":164,"rank_vocals":218,"rating":2,"song_id":5038,"song_length":211975,"sub_genre":"subgenre_rock","vocal_gender":"male","vocal_parts":3,"vocal_tonic_note":4,"year_released":2013},{"id":"atnightindreams","name":"At Night in Dreams","artist":"White Denim","album_name":"Corsicana Lemonade","anim_tempo":64,"game_origin":"rb4","genre":"indierock","master":true,"rank_band":326,"rank_bass":454,"rank_drum":468,"rank_guitar":400,"rank_vocals":262,"rating":2,"song_id":5046,"song_length":247892,"sub_genre":"subgenre_indierock","vocal_gender":"male","vocal_parts":2,"vocal_tonic_note":8,"year_released":2013},{"id":"birthinreverse","name":"Birth in Reverse","artist":"St. Vincent","album_name":"St. Vincent","anim_tempo":64,"game_origin":"rb4","genre":"indierock","master":true,"rank_band":283,"rank_bass":228,"rank_drum":448,"rank_guitar":309,"rank_vocals":185,"rating":2,"song_id":5062,"song_length":201410,"sub_genre":"subgenre_indierock","vocal_gender":"female","vocal_parts":1,"vocal_tonic_note":4,"year_released":2014},{"id":"browneyedgirl","name":"Brown Eyed Girl","artist":"Van Morrison","album_name":"Blowin' Your Mind!","anim_tempo":64,"game_origin":"rb4","genre":"rbsoulfunk","master":true,"rank_band":221,"rank_bass":272,"rank_drum":130,"rank_guitar":239,"rank_vocals":361,"rating":2,"song_id":5050,"song_length":188590,"sub_genre":"subgenre_pop","vocal_gender":"male","vocal_parts":3,"vocal_tonic_note":7,"year_released":1967},{"id":"caughtupinyou","name":"Caught Up in You","artist":".38 Special","album_name":"Special Forces","anim_tempo":32,"game_origin":"rb4","genre":"southernrock","master":true,"rank_band":260,"rank_bass":170,"rank_drum":124,"rank_guitar":431,"rank_vocals":248,"rating":2,"song_id":5024,"song_length":294865,"sub_genre":"subgenre_southernrock","vocal_gender":"male","vocal_parts":2,"vocal_tonic_note":4,"year_released":1982},{"id":"cedarwoodroad","name":"Cedarwood Road","artist":"U2","album_name":"Songs of Innocence","anim_tempo":16,"game_origin":"rb4","genre":"rock","master":true,"rank_band":108,"rank_bass":108,"rank_drum":117,"rank_guitar":116,"rank_vocals":137,"rating":2,"song_id":5067,"song_length":270056,"sub_genre":"subgenre_rock","vocal_gender":"male","vocal_parts":3,"vocal_tonic_note":4,"year_released":2014},{"id":"centuries","name":"Centuries","artist":"Fall Out Boy","album_name":"American Beauty/American Psycho","anim_tempo":16,"game_origin":"rb4","genre":"poprock","master":true,"rank_band":140,"rank_bass":160,"rank_drum":123,"rank_guitar":100,"rank_keys":160,"rank_real_keys":160,"rank_vocals":279,"rating":2,"song_id":5030,"song_length":242783,"song_tonality":0,"sub_genre":"subgenre_softrock","vocal_gender":"male","vocal_parts":3,"vocal_tonic_note":4,"year_released":2015},{"id":"coldclearlight","name":"Cold Clear Light","artist":"Johnny Blazes and The Pretty Boys","album_name":"Soul Vernacular","anim_tempo":16,"game_origin":"rb4","genre":"rbsoulfunk","master":true,"rank_band":277,"rank_bass":214,"rank_drum":166,"rank_guitar":295,"rank_vocals":469,"rating":2,"song_id":5063,"song_length":277017,"sub_genre":"subgenre_funk","vocal_gender":"male","vocal_parts":3,"vocal_tonic_note":9,"year_released":2015},{"id":"deadblack","name":"Dead Black (Heart of Ice)","artist":"Soul Remnants","album_name":"Black & Blood","anim_tempo":64,"game_origin":"rb4","genre":"metal","master":true,"rank_band":457,"rank_bass":472,"rank_drum":490,"rank_guitar":420,"rank_vocals":100,"rating":2,"song_id":5056,"song_length":481364,"sub_genre":"subgenre_death","vocal_gender":"male","vocal_parts":1,"vocal_tonic_note":9,"year_released":2013},{"id":"dreamgenie","name":"Dream Genie","artist":"Lightning Bolt","album_name":"Fantasy Empire","anim_tempo":64,"game_origin":"rb4","genre":"rock","master":true,"rank_band":474,"rank_bass":480,"rank_drum":500,"rank_guitar":422,"rank_real_bass":442,"rank_real_guitar":442,"rank_vocals":441,"rating":2,"song_id":5068,"song_length":386302,"sub_genre":"subgenre_other","vocal_gender":"male","vocal_parts":1,"vocal_tonic_note":2,"year_released":2015},{"id":"feastandthefamine","name":"The Feast and the Famine","artist":"Foo Fighters","album_name":"Sonic Highways","anim_tempo":64,"game_origin":"rb4","genre":"alternative","master":true,"rank_band":254,"rank_bass":242,"rank_drum":344,"rank_guitar":220,"rank_vocals":255,"rating":2,"song_id":5020,"song_length":233147,"sub_genre":"subgenre_alternative","vocal_gender":"male","vocal_parts":3,"vocal_tonic_note":11,"year_released":2014},{"id":"fever_bk","name":"Fever","artist":"The Black Keys","album_name":"Turn Blue","anim_tempo":32,"game_origin":"rb4","genre":"rock","master":true,"rank_band":116,"rank_bass":181,"rank_drum":111,"rank_guitar":108,"rank_vocals":109,"rating":2,"song_id":5006,"song_length":250647,"sub_genre":"subgenre_rock","vocal_gender":"male","vocal_parts":2,"vocal_tonic_note":9,"year_released":2014},{"id":"followyoudown","name":"Follow You Down","artist":"Gin Blossoms","album_name":"Congratulations I'm Sorry","anim_tempo":64,"game_origin":"rb4","genre":"alternative","master":true,"rank_band":228,"rank_bass":380,"rank_drum":286,"rank_guitar":194,"rank_vocals":142,"rating":2,"song_id":5035,"song_length":270401,"sub_genre":"subgenre_alternative","vocal_gender":"male","vocal_parts":3,"vocal_tonic_note":7,"year_released":1996},{"id":"freefallingwarning","name":"Free Falling","artist":"The Warning","album_name":"Escape the Mind","anim_tempo":32,"game_origin":"rb4","genre":"rock","master":true,"rank_band":100,"rank_bass":127,"rank_drum":103,"rank_guitar":104,"rank_vocals":121,"rating":2,"song_id":5064,"song_length":237622,"sub_genre":"subgenre_rock","vocal_gender":"female","vocal_parts":3,"vocal_tonic_note":5,"year_released":2015},{"id":"fridayiminlove","name":"Friday I'm in Love","artist":"The Cure","album_name":"Wish","anim_tempo":32,"game_origin":"rb4","genre":"new_wave","master":true,"rank_band":165,"rank_bass":104,"rank_drum":145,"rank_guitar":188,"rank_vocals":270,"rating":2,"song_id":5031,"song_length":215315,"sub_genre":"subgenre_other","vocal_gender":"male","vocal_parts":3,"vocal_tonic_note":2,"year_released":1992},{"id":"hailtotheking","name":"Hail to the King","artist":"Avenged Sevenfold","album_name":"Hail to the King","anim_tempo":32,"game_origin":"rb4","genre":"metal","master":true,"rank_band":286,"rank_bass":120,"rank_drum":100,"rank_guitar":440,"rank_vocals":113,"rating":2,"song_id":5019,"song_length":307117,"sub_genre":"subgenre_metal","vocal_gender":"male","vocal_parts":3,"vocal_tonic_note":3,"year_released":2013},{"id":"hallsofvalhalla","name":"Halls of Valhalla","artist":"Judas Priest","album_name":"Redeemer of Souls","anim_tempo":16,"game_origin":"rb4","genre":"metal","master":true,"rank_band":425,"rank_bass":419,"rank_drum":330,"rank_guitar":445,"rank_vocals":434,"rating":2,"song_id":5009,"song_length":361126,"sub_genre":"subgenre_metal","vocal_gender":"male","vocal_parts":3,"vocal_tonic_note":3,"year_released":2014},{"id":"iamelectric","name":"I Am Electric","artist":"Heaven's Basement","album_name":"Filthy Empire","anim_tempo":64,"game_origin":"rb4","genre":"rock","master":true,"rank_band":242,"rank_bass":191,"rank_drum":452,"rank_guitar":168,"rank_vocals":132,"rating":3,"song_id":5053,"song_length":184508,"sub_genre":"subgenre_rock","vocal_gender":"male","vocal_parts":2,"vocal_tonic_note":5,"year_released":2013},{"id":"ibetmylife","name":"I Bet My Life","artist":"Imagine Dragons","album_name":"Smoke + Mirrors","anim_tempo":32,"game_origin":"rb4","genre":"alternative","master":true,"rank_band":214,"rank_bass":100,"rank_drum":148,"rank_guitar":260,"rank_vocals":426,"rating":2,"song_id":5003,"song_length":196663,"sub_genre":"subgenre_alternative","vocal_gender":"male","vocal_parts":3,"vocal_tonic_note":1,"year_released":2015},{"id":"imissthemisery","name":"I Miss the Misery","artist":"Halestorm","album_name":"The Strange Case Of...","anim_tempo":16,"game_origin":"rb4","genre":"rock","master":true,"rank_band":266,"rank_bass":292,"rank_drum":232,"rank_guitar":215,"rank_keys":176,"rank_real_keys":176,"rank_vocals":352,"rating":2,"song_id":5047,"song_length":188778,"song_tonality":0,"sub_genre":"subgenre_rock","vocal_gender":"female","vocal_parts":3,"vocal_tonic_note":9,"year_released":2012},{"id":"iwillfollow","name":"I Will Follow","artist":"U2","album_name":"Boy","anim_tempo":64,"game_origin":"rb4","genre":"rock","master":true,"rank_band":124,"rank_bass":128,"rank_drum":169,"rank_guitar":112,"rank_vocals":106,"rating":2,"song_id":5066,"song_length":218104,"sub_genre":"subgenre_rock","vocal_gender":"male","vocal_parts":2,"vocal_tonic_note":3,"year_released":1980},{"id":"kickitout","name":"Kick It Out","artist":"Heart","album_name":"Little Queen","anim_tempo":64,"game_origin":"rb4","genre":"classicrock","master":true,"rank_band":320,"rank_bass":328,"rank_drum":275,"rank_guitar":266,"rank_vocals":417,"rating":2,"song_id":5032,"song_length":165385,"sub_genre":"subgenre_classicrock","vocal_gender":"female","vocal_parts":2,"vocal_tonic_note":9,"year_released":1977},{"id":"knockemdown","name":"Knock Em Down","artist":"Duck & Cover","album_name":"Duck & Cover","anim_tempo":64,"game_origin":"rb4","genre":"punk","master":true,"rank_band":344,"rank_bass":310,"rank_drum":456,"rank_guitar":302,"rank_vocals":322,"rating":2,"song_id":5042,"song_length":155192,"sub_genre":"subgenre_punk","vocal_gender":"male","vocal_parts":1,"vocal_tonic_note":11,"year_released":2014},{"id":"lazaretto","name":"Lazaretto","artist":"Jack White","album_name":"Lazaretto","anim_tempo":16,"game_origin":"rb4","genre":"rock","master":true,"rank_band":296,"rank_bass":395,"rank_drum":319,"rank_guitar":281,"rank_vocals":217,"rating":2,"song_id":5017,"song_length":222943,"sub_genre":"subgenre_rock","vocal_gender":"male","vocal_parts":2,"vocal_tonic_note":6,"year_released":2014},{"id":"lightthefuse","name":"Light the Fuse","artist":"Slydigs","album_name":"Light the Fuse","anim_tempo":32,"game_origin":"rb4","genre":"rock","master":true,"rank_band":218,"rank_bass":145,"rank_drum":308,"rank_guitar":233,"rank_vocals":147,"rating":2,"song_id":5043,"song_length":246373,"sub_genre":"subgenre_rock","vocal_gender":"male","vocal_parts":2,"vocal_tonic_note":11,"year_released":2015},{"id":"lightupthenight","name":"Light Up the Night","artist":"The Protomen","album_name":"Act II: The Father of Death","anim_tempo":64,"game_origin":"rb4","genre":"rock","master":true,"rank_band":225,"rank_bass":165,"rank_drum":218,"rank_guitar":182,"rank_vocals":485,"rating":2,"song_id":5061,"song_length":254284,"sub_genre":"subgenre_rock","vocal_gender":"male","vocal_parts":3,"vocal_tonic_note":1,"year_released":2009},{"id":"littlemisscantbewrong","name":"Little Miss Can't Be Wrong","artist":"Spin Doctors","album_name":"Pocket Full of Kryptonite","anim_tempo":32,"game_origin":"rb4","genre":"alternative","master":true,"rank_band":377,"rank_bass":466,"rank_drum":120,"rank_guitar":349,"rank_vocals":378,"rating":2,"song_id":5002,"song_length":236838,"sub_genre":"subgenre_alternative","vocal_gender":"male","vocal_parts":3,"vocal_tonic_note":7,"year_released":1991},{"id":"littlewhitechurch","name":"Little White Church","artist":"Little Big Town","album_name":"The Reason Why","anim_tempo":32,"game_origin":"rb4","genre":"country","master":true,"rank_band":148,"rank_bass":180,"rank_drum":108,"rank_guitar":175,"rank_vocals":225,"rating":2,"song_id":5013,"song_length":190648,"sub_genre":"subgenre_country","vocal_gender":"female","vocal_parts":3,"vocal_tonic_note":5,"year_released":2010},{"id":"mainstreamkid","name":"Mainstream Kid","artist":"Brandi Carlile","album_name":"The Firewatcher's Daughter","anim_tempo":32,"game_origin":"rb4","genre":"rock","master":true,"rank_band":238,"rank_bass":288,"rank_drum":175,"rank_guitar":373,"rank_vocals":240,"rating":2,"song_id":5051,"song_length":262753,"sub_genre":"subgenre_blues","vocal_gender":"female","vocal_parts":3,"vocal_tonic_note":9,"year_released":2015},{"id":"metropolis","name":"Metropolis - Part 1 \"The Miracle and the Sleeper\"","artist":"Dream Theater","album_name":"Images and Words","anim_tempo":32,"game_origin":"rb4","genre":"prog","master":true,"rank_band":490,"rank_bass":495,"rank_drum":480,"rank_guitar":480,"rank_keys":443,"rank_real_keys":443,"rank_vocals":478,"rating":1,"song_id":5016,"song_length":573997,"vocal_gender":"male","vocal_parts":2,"vocal_tonic_note":4,"year_released":1992},{"id":"milwaukee","name":"Milwaukee","artist":"The Both","album_name":"The Both","anim_tempo":64,"game_origin":"rb4","genre":"poprock","master":true,"rank_band":234,"rank_bass":334,"rank_drum":210,"rank_guitar":333,"rank_vocals":195,"rating":2,"song_id":5058,"song_length":263291,"sub_genre":"subgenre_pop","vocal_gender":"female","vocal_parts":2,"vocal_tonic_note":9,"year_released":2014},{"id":"miracleman","name":"Miracle Man","artist":"Ozzy Osbourne","album_name":"No Rest for the Wicked","anim_tempo":32,"game_origin":"rb4","genre":"metal","master":true,"rank_band":345,"rank_bass":428,"rank_drum":460,"rank_guitar":408,"rank_vocals":158,"rating":2,"song_id":5059,"song_length":228843,"sub_genre":"subgenre_metal","vocal_gender":"male","vocal_parts":2,"vocal_tonic_note":5,"year_released":1988},{"id":"mygodisthesun","name":"My God is the Sun","artist":"Queens of the Stone Age","album_name":"...Like Clockwork","anim_tempo":64,"game_origin":"rb4","genre":"alternative","master":true,"rank_band":275,"rank_bass":363,"rank_drum":389,"rank_guitar":252,"rank_real_bass":208,"rank_real_guitar":267,"rank_vocals":303,"rating":1,"song_id":380990074,"song_length":224240,"sub_genre":"subgenre_alternative","vocal_gender":"male","vocal_parts":2,"vocal_tonic_note":4,"year_released":2013},{"id":"noonelikeyou","name":"No One Like You","artist":"Scorpions","album_name":"Comeblack","anim_tempo":32,"game_origin":"rb4","genre":"metal","master":true,"rank_band":231,"rank_bass":135,"rank_drum":136,"rank_guitar":365,"rank_vocals":131,"rating":2,"song_id":5033,"song_length":250343,"sub_genre":"subgenre_metal","vocal_gender":"male","vocal_parts":3,"vocal_tonic_note":7,"year_released":2011},{"id":"panama","name":"Panama","artist":"Van Halen","album_name":"1984","anim_tempo":32,"game_origin":"rb4","genre":"rock","master":true,"rank_band":251,"rank_bass":403,"rank_drum":177,"rank_guitar":341,"rank_vocals":180,"rating":2,"song_id":5065,"song_length":211660,"sub_genre":"subgenre_rock","vocal_gender":"male","vocal_parts":3,"vocal_tonic_note":3,"year_released":1984},{"id":"pistolwhipped","name":"Pistol Whipped","artist":"Tijuana Sweetheart","album_name":"Under the Gun","anim_tempo":32,"game_origin":"rb4","genre":"punk","master":true,"rank_band":315,"rank_bass":186,"rank_drum":345,"rank_guitar":389,"rank_vocals":174,"rating":2,"song_id":5054,"song_length":151990,"sub_genre":"subgenre_punk","vocal_gender":"female","vocal_parts":3,"vocal_tonic_note":8,"year_released":2012},{"id":"prayer","name":"Prayer","artist":"Disturbed","album_name":"Believe","anim_tempo":16,"game_origin":"rb4","genre":"numetal","master":true,"rank_band":273,"rank_bass":227,"rank_drum":433,"rank_guitar":245,"rank_vocals":206,"rating":2,"song_id":5008,"song_length":225406,"sub_genre":"subgenre_numetal","vocal_gender":"male","vocal_parts":3,"vocal_tonic_note":1,"year_released":2002},{"id":"recession","name":"Recession (ft. Noelle LeBlanc and Naoko Takamoto)","artist":"Jeff Allen","album_name":"As featured in Amplitude","anim_tempo":32,"game_origin":"rb4","genre":"popdanceelectronic","master":true,"rank_band":393,"rank_bass":460,"rank_drum":472,"rank_guitar":357,"rank_vocals":287,"rating":1,"song_id":5001,"song_length":228968,"sub_genre":"subgenre_electronica","vocal_gender":"female","vocal_parts":3,"vocal_tonic_note":6,"year_released":2015},{"id":"rockandrollhoochiekoo","name":"Rock and Roll, Hoochie Koo","artist":"Rick Derringer","album_name":"All American Boy","anim_tempo":32,"game_origin":"rb4","genre":"classicrock","master":true,"rank_band":441,"rank_bass":486,"rank_drum":367,"rank_guitar":430,"rank_vocals":448,"rating":2,"song_id":5018,"song_length":227132,"sub_genre":"subgenre_classicrock","vocal_gender":"male","vocal_parts":3,"vocal_tonic_note":9,"year_released":1973},{"id":"shortskirtlongjacket","name":"Short Skirt/Long Jacket","artist":"Cake","album_name":"Comfort Eagle","anim_tempo":32,"game_origin":"rb4","genre":"alternative","master":true,"rank_band":177,"rank_bass":345,"rank_drum":133,"rank_guitar":205,"rank_keys":1,"rank_real_bass":325,"rank_real_guitar":208,"rank_real_keys":1,"rank_vocals":103,"rating":2,"song_id":5028,"song_length":204021,"sub_genre":"subgenre_alternative","vocal_gender":"male","vocal_parts":3,"vocal_tonic_note":2,"year_released":2001},{"id":"somebodytoldme","name":"Somebody Told Me","artist":"The Killers","album_name":"Hot Fuss","anim_tempo":32,"game_origin":"rb4","genre":"alternative","master":true,"rank_band":310,"rank_bass":364,"rank_drum":464,"rank_guitar":221,"rank_keys":211,"rank_real_bass":325,"rank_real_guitar":267,"rank_real_keys":211,"rank_vocals":190,"rating":2,"song_id":5011,"song_length":201809,"sub_genre":"subgenre_alternative","vocal_gender":"male","vocal_parts":3,"vocal_tonic_note":10,"year_released":2004},{"id":"spiders","name":"Spiders","artist":"System of a Down","album_name":"System of a Down","anim_tempo":32,"game_origin":"rb4","genre":"numetal","master":true,"rank_band":189,"rank_bass":155,"rank_drum":163,"rank_guitar":144,"rank_vocals":342,"rating":2,"song_id":5060,"song_length":222498,"sub_genre":"subgenre_metal","vocal_gender":"male","vocal_parts":3,"vocal_tonic_note":0,"year_released":1998},{"id":"startaband","name":"Start a Band (ft. Keith Urban)","artist":"Brad Paisley","album_name":"Play","anim_tempo":32,"game_origin":"rb4","genre":"country","master":true,"rank_band":332,"rank_bass":202,"rank_drum":202,"rank_guitar":435,"rank_vocals":379,"rating":2,"song_id":5036,"song_length":304955,"sub_genre":"subgenre_country","vocal_gender":"male","vocal_parts":3,"vocal_tonic_note":5,"year_released":2008},{"id":"stillintoyou","name":"Still Into You","artist":"Paramore","album_name":"Paramore","anim_tempo":32,"game_origin":"rb4","genre":"poprock","master":true,"rank_band":279,"rank_bass":372,"rank_drum":241,"rank_guitar":172,"rank_keys":327,"rank_real_bass":267,"rank_real_guitar":209,"rank_real_keys":327,"rank_vocals":427,"rating":1,"song_id":5034,"song_length":212645,"song_tonality":0,"sub_genre":"subgenre_other","vocal_gender":"female","vocal_parts":2,"vocal_tonic_note":5,"year_released":2013},{"id":"superunknownrb4","name":"Superunknown","artist":"Soundgarden","album_name":"Superunknown","anim_tempo":32,"game_origin":"rb4","genre":"grunge","master":true,"rank_band":281,"rank_bass":234,"rank_drum":194,"rank_guitar":409,"rank_vocals":313,"rating":2,"song_id":5048,"song_length":312224,"sub_genre":"subgenre_grunge","vocal_gender":"male","vocal_parts":2,"vocal_tonic_note":7,"year_released":1994},{"id":"suspiciousminds","name":"Suspicious Minds","artist":"Elvis Presley","album_name":"From Elvis in Memphis","anim_tempo":32,"game_origin":"rb4","genre":"rock","master":true,"rank_band":248,"rank_bass":435,"rank_drum":114,"rank_guitar":316,"rank_vocals":200,"rating":1,"song_id":5012,"song_length":270930,"sub_genre":"subgenre_rock","vocal_gender":"male","vocal_parts":3,"vocal_tonic_note":7,"year_released":1969},{"id":"thatsmell","name":"That Smell","artist":"Lynyrd Skynyrd","album_name":"Street Survivors","anim_tempo":32,"game_origin":"rb4","genre":"southernrock","master":true,"rank_band":409,"rank_bass":411,"rank_drum":242,"rank_guitar":417,"rank_vocals":455,"rating":3,"song_id":5014,"song_length":347552,"sub_genre":"subgenre_southernrock","vocal_gender":"male","vocal_parts":3,"vocal_tonic_note":9,"year_released":1977},{"id":"theimpressionthatiget","name":"The Impression That I Get","artist":"The Mighty Mighty Bosstones","album_name":"Let's Face It","anim_tempo":64,"game_origin":"rb4","genre":"reggaeska","master":true,"rank_band":338,"rank_bass":442,"rank_drum":411,"rank_guitar":323,"rank_keys":211,"rank_real_keys":211,"rank_vocals":212,"rating":2,"song_id":5037,"song_length":196167,"sub_genre":"subgenre_ska","vocal_gender":"male","vocal_parts":2,"vocal_tonic_note":4,"year_released":1997},{"id":"theoneilove","name":"The One I Love","artist":"R.E.M.","album_name":"Document","anim_tempo":32,"game_origin":"rb4","genre":"alternative","master":true,"rank_band":132,"rank_bass":134,"rank_drum":150,"rank_guitar":138,"rank_vocals":117,"rating":2,"song_id":5039,"song_length":200874,"sub_genre":"subgenre_alternative","vocal_gender":"male","vocal_parts":3,"vocal_tonic_note":4,"year_released":1987},{"id":"theseeker","name":"The Seeker","artist":"The Who","album_name":"Meaty Beaty Big and Bouncy","anim_tempo":16,"game_origin":"rb4","genre":"classicrock","master":true,"rank_band":267,"rank_bass":336,"rank_drum":224,"rank_guitar":332,"rank_vocals":175,"rating":2,"song_id":5022,"song_length":201072,"sub_genre":"subgenre_rock","vocal_gender":"male","vocal_parts":3,"vocal_tonic_note":9,"year_released":1971},{"id":"thewarrior","name":"The Warrior","artist":"Scandal","album_name":"Warrior","anim_tempo":32,"game_origin":"rb4","genre":"rock","master":true,"rank_band":164,"rank_bass":140,"rank_drum":172,"rank_guitar":149,"rank_vocals":233,"rating":1,"song_id":5029,"song_length":249534,"sub_genre":"subgenre_rock","vocal_gender":"female","vocal_parts":3,"vocal_tonic_note":2,"year_released":1984},{"id":"thewolf","name":"The Wolf","artist":"Mumford & Sons","album_name":"Wilder Mind","anim_tempo":64,"game_origin":"rb4","genre":"rock","master":true,"rank_band":171,"rank_bass":197,"rank_drum":264,"rank_guitar":125,"rank_vocals":169,"rating":2,"song_id":5044,"song_length":221175,"sub_genre":"subgenre_rock","vocal_gender":"male","vocal_parts":3,"vocal_tonic_note":2,"year_released":2015},{"id":"tonguetied","name":"Tongue Tied","artist":"Grouplove","album_name":"Never Trust a Happy Song","anim_tempo":32,"game_origin":"rb4","genre":"indierock","master":true,"rank_band":257,"rank_bass":208,"rank_drum":400,"rank_guitar":139,"rank_keys":269,"rank_real_keys":269,"rank_vocals":153,"rating":2,"song_id":5069,"song_length":220883,"song_tonality":0,"sub_genre":"subgenre_indierock","vocal_gender":"male","vocal_parts":3,"vocal_tonic_note":3,"year_released":2011},{"id":"toysintheattic","name":"Toys in the Attic","artist":"Aerosmith","album_name":"Toys in the Attic","anim_tempo":64,"game_origin":"rb4","genre":"rock","master":true,"rank_band":361,"rank_bass":448,"rank_drum":356,"rank_guitar":381,"rank_vocals":353,"rating":2,"song_id":5070,"song_length":188080,"sub_genre":"subgenre_rock","vocal_gender":"male","vocal_parts":3,"vocal_tonic_note":4,"year_released":1975},{"id":"turnitaround","name":"Turn It Around","artist":"Lucius","album_name":"Wildewoman","anim_tempo":32,"game_origin":"rb4","genre":"indierock","master":true,"rank_band":208,"rank_bass":319,"rank_drum":160,"rank_guitar":133,"rank_vocals":330,"rating":2,"song_id":5049,"song_length":215304,"sub_genre":"subgenre_indierock","vocal_gender":"female","vocal_parts":3,"vocal_tonic_note":2,"year_released":2013},{"id":"uptownfunk","name":"Uptown Funk (ft. Bruno Mars)","artist":"Mark Ronson","album_name":"Uptown Special","anim_tempo":32,"game_origin":"rb4","genre":"rbsoulfunk","master":true,"rank_band":243,"rank_bass":250,"rank_drum":157,"rank_guitar":154,"rank_vocals":462,"rating":2,"song_id":5021,"song_length":275472,"sub_genre":"subgenre_other","vocal_gender":"male","vocal_parts":3,"vocal_tonic_note":2,"year_released":2015},{"id":"vbomb","name":"V-Bomb","artist":"Dark Wheels","album_name":"Mighty Sky","anim_tempo":32,"game_origin":"rb4","genre":"rock","master":true,"rank_band":202,"rank_bass":264,"rank_drum":178,"rank_guitar":159,"rank_vocals":126,"rating":2,"song_id":5041,"song_length":277893,"sub_genre":"subgenre_rock","vocal_gender":"male","vocal_parts":3,"vocal_tonic_note":4,"year_released":2015},{"id":"violentshiver","name":"Violent Shiver","artist":"Benjamin Booker","album_name":"Benjamin Booker","anim_tempo":64,"game_origin":"rb4","genre":"rock","master":true,"rank_band":304,"rank_bass":293,"rank_drum":378,"rank_guitar":263,"rank_vocals":394,"rating":2,"song_id":5052,"song_length":171003,"sub_genre":"subgenre_rock","vocal_gender":"male","vocal_parts":3,"vocal_tonic_note":1,"year_released":2014},{"id":"whatsup","name":"What's Up?","artist":"4 Non Blondes","album_name":"Bigger, Better, Faster, More!","anim_tempo":16,"game_origin":"rb4","genre":"alternative","master":true,"rank_band":156,"rank_bass":116,"rank_drum":105,"rank_guitar":120,"rank_keys":85,"rank_real_bass":322,"rank_real_guitar":168,"rank_real_keys":85,"rank_vocals":492,"rating":1,"song_id":5023,"song_length":300471,"song_tonality":0,"sub_genre":"subgenre_alternative","vocal_gender":"female","vocal_parts":2,"vocal_tonic_note":9,"year_released":1992},{"id":"youmakelovingfun","name":"You Make Loving Fun","artist":"Fleetwood Mac","album_name":"Rumours","anim_tempo":32,"game_origin":"rb4","genre":"classicrock","master":true,"rank_band":195,"rank_bass":220,"rank_drum":142,"rank_guitar":176,"rank_vocals":386,"rating":2,"song_id":5015,"song_length":221930,"sub_genre":"subgenre_rock","vocal_gender":"female","vocal_parts":3,"vocal_tonic_note":10,"year_released":1977},{"id":"yourlove","name":"Your Love","artist":"The Outfield","album_name":"Play Deep","anim_tempo":32,"game_origin":"rb4","genre":"poprock","master":true,"rank_band":183,"rank_bass":112,"rank_drum":139,"rank_guitar":227,"rank_real_bass":110,"rank_real_guitar":208,"rank_vocals":295,"rating":1,"song_id":5004,"song_length":218745,"sub_genre":"subgenre_other","vocal_gender":"male","vocal_parts":3,"vocal_tonic_note":4,"year_released":1985}]